LICENSE
MANIFEST.in
README
setup.py
thornbed/__init__.py
thornbed/version.py
thornbed.egg-info/PKG-INFO
thornbed.egg-info/SOURCES.txt
thornbed.egg-info/dependency_links.txt
thornbed.egg-info/entry_points.txt
thornbed.egg-info/not-zip-safe
thornbed.egg-info/requires.txt
thornbed.egg-info/top_level.txt
thornbed/services/__init__.py
thornbed/services/flickr.py
thornbed/services/imgur.py
thornbed/services/quickmeme.py
thornbed/services/vimeo.py
thornbed/services/youtube.py