Metadata-Version: 1.1
Name: thornbed
Version: 0.4.4
Summary: Simple oEmbed wrapper for different services
Home-page: https://bitbucket.org/eka/thornbed
Author: Esteban Feldman
Author-email: esteban.feldman@gmail.com
License: BSD
Keywords: oembed youtube vimeo imgur flickr quickmeme
Platform: UNKNOWN
Classifier: Intended Audience :: Developers
Classifier: License :: OSI Approved :: BSD License
Classifier: Operating System :: OS Independent
Classifier: Programming Language :: Python
Classifier: Topic :: Internet :: WWW/HTTP :: Dynamic Content
